pytodcor/__init__.py
pytodcor/lib/__init__.py
pytodcor/lib/spectrum.py
pytodcor/model/__init__.py
pytodcor/model/load_model.py
pytodcor/model/match_model.py
pytodcor/model/read_model_bosz.py
pytodcor/model/read_model_kurucz.py
pytodcor/obs/__init__.py
pytodcor/obs/load_spectrum.py
pytodcor/obs/read_spec_apogee.py
pytodcor/obs/read_spec_arc35.py
pytodcor/xcor/__init__.py
pytodcor/xcor/todcor.py
pytodcor/xcor/xcor1d.py
pytodcor-0.1.dist-info/licenses/LICENSE
pytodcor-0.1.dist-info/METADATA
pytodcor-0.1.dist-info/WHEEL
pytodcor-0.1.dist-info/top_level.txt
pytodcor-0.1.dist-info/RECORD
